flowprompt/__init__.py
flowprompt/py.typed
flowprompt/cli/__init__.py
flowprompt/cli/main.py
flowprompt/core/__init__.py
flowprompt/core/cache.py
flowprompt/core/field.py
flowprompt/core/prompt.py
flowprompt/core/streaming.py
flowprompt/multimodal/__init__.py
flowprompt/multimodal/content.py
flowprompt/multimodal/prompt.py
flowprompt/optimize/__init__.py
flowprompt/optimize/examples.py
flowprompt/optimize/metrics.py
flowprompt/optimize/optimizer.py
flowprompt/providers/__init__.py
flowprompt/providers/base.py
flowprompt/providers/litellm.py
flowprompt/storage/__init__.py
flowprompt/storage/yaml_loader.py
flowprompt/testing/__init__.py
flowprompt/testing/allocation.py
flowprompt/testing/experiment.py
flowprompt/testing/runner.py
flowprompt/testing/statistics.py
flowprompt/tracing/__init__.py
flowprompt/tracing/otel.py
flowprompt_ai-0.2.1.dist-info/METADATA
flowprompt_ai-0.2.1.dist-info/WHEEL
flowprompt_ai-0.2.1.dist-info/entry_points.txt
flowprompt_ai-0.2.1.dist-info/licenses/LICENSE
flowprompt_ai-0.2.1.dist-info/RECORD
