Metadata-Version: 2.4
Name: flowprompt-ai
Version: 0.2.1
Summary: Type-safe prompt management with automatic optimization for LLMs
Project-URL: Homepage, https://github.com/yotambraun/flowprompt
Project-URL: Documentation, https://github.com/yotambraun/flowprompt/tree/main/docs
Project-URL: Repository, https://github.com/yotambraun/flowprompt
Project-URL: Changelog, https://github.com/yotambraun/flowprompt/blob/main/CHANGELOG.md
Project-URL: Issues, https://github.com/yotambraun/flowprompt/issues
Project-URL: Source Code, https://github.com/yotambraun/flowprompt
Author-email: Yotam Braun <yotambarun93@gmail.com>
Maintainer-email: Yotam Braun <yotambarun93@gmail.com>
License: MIT
License-File: LICENSE
Keywords: a-b-testing,ai,anthropic,chatgpt,claude,gpt,langchain-alternative,litellm,llm,llm-framework,machine-learning,nlp,observability,openai,prompt,prompt-engineering,prompt-management,prompt-optimization,prompt-testing,prompt-versioning,pydantic,structured-output,type-safety
Classifier: Development Status :: 4 - Beta
Classifier: Environment :: Console
Classifier: Framework :: Pydantic :: 2
Classifier: Intended Audience :: Developers
Classifier: Intended Audience :: Science/Research
Classifier: License :: OSI Approved :: MIT License
Classifier: Natural Language :: English
Classifier: Operating System :: OS Independent
Classifier: Programming Language :: Python :: 3
Classifier: Programming Language :: Python :: 3 :: Only
Classifier: Programming Language :: Python :: 3.10
Classifier: Programming Language :: Python :: 3.11
Classifier: Programming Language :: Python :: 3.12
Classifier: Programming Language :: Python :: 3.13
Classifier: Topic :: Scientific/Engineering :: Artificial Intelligence
Classifier: Topic :: Software Development :: Libraries :: Python Modules
Classifier: Topic :: Text Processing :: Linguistic
Classifier: Typing :: Typed
Requires-Python: >=3.10
Requires-Dist: jinja2<4.0.0,>=3.0.0
Requires-Dist: litellm<2.0.0,>=1.0.0
Requires-Dist: pydantic<3.0.0,>=2.0.0
Requires-Dist: pyyaml<7.0.0,>=6.0.0
Requires-Dist: typing-extensions>=4.5.0; python_version < '3.11'
Provides-Extra: all
Requires-Dist: opencv-python>=4.8.0; extra == 'all'
Requires-Dist: opentelemetry-api>=1.20.0; extra == 'all'
Requires-Dist: opentelemetry-sdk>=1.20.0; extra == 'all'
Requires-Dist: optuna>=3.5.0; extra == 'all'
Requires-Dist: pypdf>=3.15.0; extra == 'all'
Requires-Dist: typer>=0.9.0; extra == 'all'
Provides-Extra: cli
Requires-Dist: typer>=0.9.0; extra == 'cli'
Provides-Extra: dev
Requires-Dist: mypy>=1.8.0; extra == 'dev'
Requires-Dist: pre-commit>=3.6.0; extra == 'dev'
Requires-Dist: pytest-asyncio>=0.23.0; extra == 'dev'
Requires-Dist: pytest-cov>=4.1.0; extra == 'dev'
Requires-Dist: pytest-mock>=3.12.0; extra == 'dev'
Requires-Dist: pytest>=8.0.0; extra == 'dev'
Requires-Dist: ruff>=0.1.0; extra == 'dev'
Requires-Dist: typer>=0.9.0; extra == 'dev'
Requires-Dist: types-requests; extra == 'dev'
Provides-Extra: multimodal
Requires-Dist: opencv-python>=4.8.0; extra == 'multimodal'
Requires-Dist: pypdf>=3.15.0; extra == 'multimodal'
Provides-Extra: optimization
Requires-Dist: optuna>=3.5.0; extra == 'optimization'
Provides-Extra: tracing
Requires-Dist: opentelemetry-api>=1.20.0; extra == 'tracing'
Requires-Dist: opentelemetry-sdk>=1.20.0; extra == 'tracing'
